logic/__init__.py
logic/cli.py
logic/operaciones.py
test_clik-0.0.3.dist-info/METADATA
test_clik-0.0.3.dist-info/WHEEL
test_clik-0.0.3.dist-info/entry_points.txt
test_clik-0.0.3.dist-info/top_level.txt
test_clik-0.0.3.dist-info/RECORD
