Metadata-Version: 2.1
Name: test-clik
Version: 0.0.3
Summary: Web Boilerplate for Flet Library
Home-page: https://github.com/dxsxsx
Author: Dxsxsx
Author-email: psdd@pm.me
Keywords: python web template,web application,development
Classifier: Programming Language :: Python :: 3
Classifier: License :: OSI Approved :: MIT License
Classifier: Operating System :: OS Independent
Requires-Dist: click
Requires-Dist: flet
